evp001/__init__.py
evp001/an0_exploratory.py
evp001/an1_health.py
evp001/an2_colour.py
evp001/an3_phenols.py
evp001/due.py
evp001/hw9.py
evp001/shablona.py
evp001/version.py
evp001/data/wine.data
evp001/tests/__init__.py
evp001/tests/test_evp001.py
evp001-0.1.dev0.dist-info/LICENSE
evp001-0.1.dev0.dist-info/METADATA
evp001-0.1.dev0.dist-info/WHEEL
evp001-0.1.dev0.dist-info/top_level.txt
evp001-0.1.dev0.dist-info/RECORD
