Metadata-Version: 2.1
Name: evp001
Version: 0.1.dev0
Summary: evp001: a template for small scientific Python projects
Home-page: http://github.com/EVP000/wk10_package
Author: Ariel Rokem
Author-email: arokem@gmail.com
Maintainer: Ariel Rokem
Maintainer-email: arokem@gmail.com
License: MIT
Platform: OS Independent
Classifier: Development Status :: 3 - Alpha
Classifier: Environment :: Console
Classifier: Intended Audience :: Science/Research
Classifier: License :: OSI Approved :: MIT License
Classifier: Operating System :: OS Independent
Classifier: Programming Language :: Python
Classifier: Topic :: Scientific/Engineering
Requires: numpy
Requires-Python: >= 3.5
Requires-Dist: numpy
